{
    "CHUTE": 228,
    "PAYER": 214,
    "STAIR": 217,
    "WOOER": 240,
    "TOTEM": 134,
    "BATTY": 115,
    "CLING": 223,
    "BLACK": 189,
    "MANOR": 233,
    "HEATH": 253,
    "GRATE": 248,
    "POWER": 240,
    "FJORD": 286,
    "ROUND": 245,
    "AUDIT": 237,
    "VODKA": 248,
    "ROBOT": 232,
    "ROGUE": 143,
    "SLAVE": 246,
    "OFFAL": 209,
    "BADLY": 81,
    "BATON": 246,
    "MOIST": 16,
    "MOULT": 104,
    "RUPEE": 19,
    "COMMA": 12,
    "CRUST": 251,
    "CHUNK": 51,
    "GREET": 233,
    "HELIX": 201,
    "PARER": 222,
    "LIVER": 239,
    "GLASS": 179,
    "SUGAR": 243,
    "PRINT": 242,
    "BENCH": 241,
    "GAUZE": 256,
    "DOZEN": 130,
    "CANNY": 126,
    "RADIO": 247,
    "AHEAD": 204,
    "MOVIE": 200,
    "LYING": 241,
    "GAILY": 249,
    "BOOZE": 217,
    "WOVEN": 159,
    "SCARE": 16,
    "GULLY": 94,
    "DIGIT": 33,
    "FRESH": 224,
    "STORE": 220,
    "TROLL": 191,
    "BRIAR": 242,
    "TRYST": 176,
    "VITAL": 60,
    "TEASE": 28,
    "AGREE": 17,
    "MADAM": 28,
    "WHELP": 236,
    "STING": 95,
    "PINTO": 24,
    "SISSY": 219,
    "ROOMY": 232,
    "ATOLL": 239,
    "PIETY": 8,
    "HUTCH": 232,
    "TRACE": 241,
    "STAND": 224,
    "UNFIT": 207,
    "CARGO": 243,
    "SOLVE": 222,
    "FLOSS": 271,
    "SHOWN": 60,
    "TREAT": 225,
    "PAUSE": 57,
    "SHOWY": 236,
    "BEADY": 242,
    "PURGE": 214,
    "BRINE": 229,
    "PROXY": 21,
    "MODEL": 222,
    "FLESH": 247,
    "GRADE": 237,
    "SPILL": 238,
    "RUDER": 161,
    "AWFUL": 244,
    "HYPER": 28,
    "TRAWL": 233,
    "GROUP": 24,
    "SHRUB": 87,
    "LEERY": 251,
    "ASKEW": 237,
    "LABEL": 265,
    "GAMMA": 252,
    "MERIT": 221,
    "BLAND": 89,
    "OCTAL": 224,
    "WROTE": 272,
    "FORTH": 230,
    "HATCH": 125,
    "FLOCK": 226,
    "SMEAR": 16,
    "HUMPH": 84,
    "CHANT": 121,
    "ABBEY": 50,
    "IVORY": 76,
    "EXULT": 257,
    "THYME": 241,
    "MOURN": 155,
    "CREPT": 233,
    "ADMIT": 78,
    "SAINT": 132,
    "STEED": 106,
    "TACIT": 243,
    "CHILL": 203,
    "GROIN": 235,
    "ABATE": 223,
    "MINCE": 125,
    "TROVE": 258,
    "COLON": 81,
    "BLURT": 235,
    "DUTCH": 248,
    "SWIRL": 244,
    "SHAKE": 235,
    "TWINE": 47,
    "TWEED": 230,
    "TIPSY": 16,
    "BELCH": 226,
    "WATCH": 228,
    "CRATE": 221,
    "ELOPE": 149,
    "CLOCK": 254,
    "MAJOR": 206,
    "FIBRE": 199,
    "YIELD": 228,
    "NAVAL": 209,
    "CHOKE": 232,
    "FELLA": 24,
    "GOLEM": 217,
    "MONEY": 84,
    "TAPIR": 186,
    "TIBIA": 228,
    "FLUME": 210,
    "EPOCH": 105,
    "FIRST": 225,
    "WHOOP": 221,
    "POKER": 244,
    "FLING": 246,
    "BADGE": 237,
    "WACKY": 262,
    "RENEW": 244,
    "SWEET": 220,
    "PILOT": 249,
    "CLOWN": 263,
    "USHER": 245,
    "VIRAL": 221,
    "TRAIT": 238,
    "LILAC": 195,
    "TRASH": 243,
    "SOWER": 234,
    "AWAKE": 250,
    "MAXIM": 98,
    "LYNCH": 24,
    "STORY": 26,
    "ALONE": 226,
    "CACAO": 236,
    "QUART": 36,
    "NYMPH": 231,
    "CLUCK": 216,
    "WORLD": 228,
    "BRISK": 188,
    "INERT": 255,
    "VOICE": 230,
    "STOVE": 244,
    "FLOOD": 181,
    "LUSTY": 47,
    "ALPHA": 102,
    "STICK": 40,
    "PRIZE": 236,
    "PLUCK": 193,
    "EVADE": 215,
    "GLORY": 228,
    "YOUTH": 237,
    "SMART": 11,
    "ASIDE": 217,
    "COYLY": 120,
    "RETCH": 18,
    "START": 32,
    "THEIR": 245,
    "VOUCH": 262,
    "FOUND": 160,
    "MIMIC": 38,
    "CHEEK": 236,
    "MARSH": 67,
    "PRIMO": 226,
    "WEDGE": 260,
    "ONSET": 73,
    "THORN": 234,
    "STALK": 135,
    "WASTE": 77,
    "GRIPE": 228,
    "LOWLY": 151,
    "SKILL": 201,
    "FIXER": 256,
    "BOBBY": 240,
    "USING": 104,
    "DRAIN": 253,
    "GAWKY": 244,
    "MONTH": 199,
    "SMELT": 260,
    "GIRTH": 118,
    "SOGGY": 238,
    "NASTY": 234,
    "KNOLL": 32,
    "OUTDO": 10,
    "ALBUM": 238,
    "GORGE": 34,
    "GONER": 103,
    "PHASE": 236,
    "TRICE": 162,
    "DONOR": 259,
    "TANGY": 70,
    "JAUNT": 241,
    "SONIC": 41,
    "BRINK": 205,
    "BELLY": 225,
    "RHYME": 231,
    "ULCER": 62,
    "PUPAL": 225,
    "PRICK": 73,
    "HEIST": 203,
    "OXIDE": 218,
    "BUGGY": 238,
    "PARRY": 209,
    "PAPER": 251,
    "KARMA": 207,
    "FEWER": 143,
    "HARRY": 228,
    "SHARD": 16,
    "CATER": 232,
    "RECAP": 232,
    "IRONY": 218,
    "STAFF": 234,
    "SERVE": 19,
    "SPIKE": 252,
    "SCOUR": 259,
    "BLUFF": 246,
    "DWARF": 232,
    "OLIVE": 244,
    "FLOAT": 215,
    "DUCHY": 206,
    "INPUT": 31,
    "DRINK": 161,
    "CRAZE": 155,
    "EGRET": 256,
    "CLASS": 257,
    "ALIEN": 26,
    "LINEN": 241,
    "WIDOW": 183,
    "BLOKE": 257,
    "APHID": 69,
    "BLUSH": 239,
    "SHALL": 115,
    "COULD": 231,
    "BRING": 244,
    "GLOAT": 191,
    "AGAPE": 227,
    "FLACK": 82,
    "SWILL": 218,
    "REACT": 222,
    "CONIC": 226,
    "ERROR": 221,
    "FLAIR": 105,
    "UNFED": 57,
    "ANGRY": 254,
    "ADOBE": 227,
    "AUGUR": 195,
    "DOUBT": 254,
    "WEARY": 47,
    "SLOSH": 121,
    "SHIRE": 57,
    "FRAME": 123,
    "TROPE": 230,
    "GLEAN": 263,
    "MOTOR": 137,
    "DEATH": 100,
    "ALLOW": 177,
    "THOSE": 250,
    "PLANT": 167,
    "FOYER": 240,
    "PULPY": 122,
    "LABOR": 221,
    "ALOFT": 241,
    "MASSE": 239,
    "TODAY": 227,
    "SURER": 203,
    "CHIEF": 42,
    "SHAME": 200,
    "DELTA": 253,
    "FORAY": 224,
    "ACUTE": 218,
    "UPSET": 241,
    "MOTTO": 231,
    "FAVOR": 58,
    "GREAT": 225,
    "PATTY": 233,
    "HOWDY": 227,
    "ECLAT": 239,
    "WRUNG": 161,
    "BRIBE": 203,
    "SLUNG": 218,
    "SAUTE": 222,
    "BANAL": 224,
    "CRASS": 216,
    "STINK": 39,
    "NATAL": 231,
    "CRIMP": 191,
    "FIELD": 252,
    "TRUSS": 33,
    "ARGUE": 257,
    "TAUNT": 93,
    "SCORN": 207,
    "HASTY": 77,
    "BREAK": 241,
    "BUTCH": 252,
    "CIVIC": 106,
    "SEEDY": 243,
    "PLEAT": 36,
    "SPICY": 216,
    "CHAMP": 103,
    "FEIGN": 50,
    "HUNKY": 7,
    "PRIDE": 223,
    "SPRAY": 18,
    "AROMA": 90,
    "BRAKE": 212,
    "ABYSS": 144,
    "LAPSE": 115,
    "PERKY": 234,
    "CLICK": 216,
    "ESSAY": 16,
    "PROVE": 201,
    "DELVE": 252,
    "OTHER": 222,
    "REPAY": 245,
    "SHAWL": 237,
    "BLOWN": 106,
    "ROYAL": 87,
    "FLICK": 226,
    "COMET": 222,
    "LEAVE": 235,
    "FARCE": 254,
    "VIVID": 244,
    "SNOUT": 203,
    "CYNIC": 108,
    "BOUGH": 244,
    "GROWL": 222,
    "BEING": 36,
    "MIDGE": 231,
    "YEARN": 65,
    "CROAK": 121,
    "STOMP": 225,
    "BASIC": 232,
    "BIOME": 119,
    "FETUS": 239,
    "NEEDY": 226,
    "FERRY": 224,
    "GRIME": 268,
    "ENEMA": 19,
    "APRON": 5,
    "RUSTY": 55,
    "TRIAD": 105,
    "CRAMP": 240,
    "STEAD": 252,
    "GLOOM": 244,
    "HINGE": 230,
    "TIGER": 205,
    "INTER": 227,
    "LOFTY": 44,
    "MARRY": 247,
    "CHEAT": 236,
    "CHARM": 166,
    "LIGHT": 52,
    "LOOPY": 236,
    "LOSER": 263,
    "AGATE": 227,
    "ABACK": 174,
    "THUMB": 61,
    "UNMET": 95,
    "HAIRY": 253,
    "POUND": 185,
    "PANIC": 232,
    "CAULK": 246,
    "ALTAR": 78,
    "LAPEL": 256,
    "ATONE": 116,
    "CRAZY": 23,
    "SQUAD": 229,
    "DEPTH": 60,
    "PITHY": 243,
    "EPOXY": 238,
    "GOOSE": 247,
    "ERODE": 76,
    "SCRAP": 9,
    "WINCE": 251,
    "PERCH": 17,
    "SHRUG": 154,
    "KHAKI": 260,
    "VIGOR": 12,
    "DROLL": 215,
    "ROBIN": 223,
    "GUILD": 242,
    "HYDRO": 48,
    "GRUEL": 225,
    "ELDER": 224,
    "FORGO": 29,
    "TWANG": 126,
    "DANDY": 222,
    "SMITE": 220,
    "UNLIT": 21,
    "TRAIN": 142,
    "TRITE": 225,
    "DEPOT": 6,
    "GOUGE": 199,
    "CINCH": 248,
    "FRONT": 230,
    "TWICE": 242,
    "AMPLE": 237,
    "GAMER": 253,
    "MOUNT": 112,
    "ZESTY": 54,
    "STOUT": 31,
    "QUIET": 3,
    "PANEL": 221,
    "BERTH": 222,
    "UNIFY": 222,
    "NIGHT": 257,
    "BLEED": 22,
    "FINER": 228,
    "WHACK": 219,
    "STOOL": 223,
    "CRANK": 233,
    "SLUMP": 225,
    "LARVA": 179,
    "FROTH": 242,
    "CLOTH": 37,
    "AGORA": 54,
    "SEVER": 226,
    "SOLAR": 231,
    "KEBAB": 247,
    "CHEST": 244,
    "ALIKE": 245,
    "OUGHT": 244,
    "FOCUS": 7,
    "LIEGE": 28,
    "HOARD": 16,
    "SOOTH": 186,
    "BOOST": 63,
    "SCALD": 209,
    "CORNY": 217,
    "SALAD": 66,
    "REBUT": 225,
    "THEME": 45,
    "FLUFF": 141,
    "GAUDY": 205,
    "POINT": 16,
    "BOOZY": 215,
    "ABASE": 199,
    "WENCH": 234,
    "CREAK": 157,
    "HUMOR": 14,
    "USURP": 10,
    "BOOBY": 216,
    "CIGAR": 200,
    "ROUGE": 189,
    "DODGE": 66,
    "DOWRY": 29,
    "METAL": 224,
    "ULTRA": 16,
    "SLOTH": 61,
    "MIDST": 14,
    "SPEND": 7,
    "ISLET": 7,
    "QUERY": 10,
    "HERON": 9,
    "TIARA": 9,
    "COAST": 8,
    "FOCAL": 20,
    "FORGE": 37,
    "PICKY": 13,
    "ASSET": 45,
    "FUNGI": 12,
    "BAYOU": 14,
    "RHINO": 8,
    "PEACH": 7,
    "HOMER": 25,
    "REBUS": 9,
    "SIEGE": 15,
    "RETRO": 5,
    "TILDE": 2
}