{
    "CHUTE": 25,
    "PAYER": 57,
    "STAIR": 25,
    "WOOER": 175,
    "TOTEM": 33,
    "BATTY": 59,
    "CLING": 57,
    "BLACK": 131,
    "MANOR": 91,
    "HEATH": 381,
    "GRATE": 23,
    "POWER": 385,
    "FJORD": 53,
    "ROUND": 48,
    "AUDIT": 50,
    "VODKA": 51,
    "ROBOT": 53,
    "SLAVE": 126,
    "OFFAL": 119,
    "BADLY": 84,
    "BATON": 88,
    "MOIST": 39,
    "FLUFF": 38,
    "MOULT": 60,
    "RUPEE": 29,
    "CRUST": 37,
    "CHUNK": 72,
    "GREET": 50,
    "HELIX": 44,
    "PARER": 49,
    "LIVER": 48,
    "MIMIC": 42,
    "GLASS": 40,
    "PRINT": 48,
    "SWILL": 71,
    "BENCH": 72,
    "GAUZE": 159,
    "DOZEN": 76,
    "CANNY": 25,
    "RADIO": 60,
    "AHEAD": 26,
    "MOVIE": 75,
    "LYING": 35,
    "GAILY": 51,
    "BOOZE": 58,
    "GULLY": 91,
    "FORGE": 49,
    "VITAL": 72,
    "TEASE": 59,
    "AGREE": 62,
    "MADAM": 31,
    "WHELP": 38,
    "STING": 49,
    "SISSY": 293,
    "ROOMY": 57,
    "ATOLL": 419,
    "HUTCH": 332,
    "TRACE": 58,
    "STAND": 44,
    "UNFIT": 68,
    "CARGO": 19,
    "SOLVE": 82,
    "FLOSS": 26,
    "STORE": 29,
    "PIETY": 24,
    "SHOWN": 123,
    "TREAT": 27,
    "IVORY": 47,
    "SHOWY": 92,
    "BEADY": 17,
    "PURGE": 33,
    "BRINE": 402,
    "PROXY": 41,
    "FLESH": 43,
    "PERCH": 49,
    "SPILL": 73,
    "RUDER": 305,
    "ENEMA": 41,
    "QUERY": 43,
    "AWFUL": 42,
    "HYPER": 65,
    "TRAWL": 32,
    "GROUP": 47,
    "SHRUB": 82,
    "LEERY": 42,
    "ASKEW": 37,
    "LABEL": 121,
    "GAMMA": 263,
    "OCTAL": 90,
    "WROTE": 56,
    "FORTH": 52,
    "FLOCK": 64,
    "SMEAR": 22,
    "HUMPH": 31,
    "CHANT": 38,
    "ABBEY": 34,
    "EXULT": 27,
    "THYME": 36,
    "TILDE": 21,
    "MOURN": 60,
    "CREPT": 34,
    "PEACH": 17,
    "ADMIT": 157,
    "SAINT": 65,
    "STEED": 32,
    "TACIT": 32,
    "ABATE": 365,
    "MINCE": 35,
    "TROVE": 83,
    "COLON": 66,
    "BLURT": 62,
    "DUTCH": 157,
    "SWIRL": 74,
    "SHAKE": 96,
    "TWINE": 58,
    "TWEED": 379,
    "TIPSY": 52,
    "BELCH": 77,
    "WATCH": 2,
    "CRATE": 52,
    "ELOPE": 42,
    "CLOCK": 63,
    "FIBRE": 35,
    "YIELD": 63,
    "NAVAL": 263,
    "CHOKE": 40,
    "HATCH": 21,
    "FELLA": 45,
    "GOLEM": 36,
    "MONEY": 83,
    "FLUME": 39,
    "FIRST": 40,
    "WHOOP": 38,
    "FLING": 52,
    "BADGE": 25,
    "WACKY": 28,
    "SWEET": 32,
    "CLUCK": 67,
    "CLOWN": 38,
    "USHER": 71,
    "VIRAL": 32,
    "TRAIT": 73,
    "LILAC": 36,
    "SOWER": 81,
    "NEEDY": 74,
    "AWAKE": 219,
    "MAXIM": 30,
    "LYNCH": 19,
    "STORY": 59,
    "ALONE": 59,
    "CACAO": 39,
    "FORGO": 58,
    "QUART": 92,
    "HOMER": 37,
    "NYMPH": 41,
    "WORLD": 66,
    "BRISK": 43,
    "INERT": 19,
    "STOVE": 46,
    "DODGE": 82,
    "FLOOD": 136,
    "COAST": 29,
    "MODEL": 30,
    "ALPHA": 50,
    "STICK": 42,
    "PRIZE": 78,
    "PLUCK": 40,
    "EVADE": 49,
    "POINT": 47,
    "GLORY": 261,
    "YOUTH": 150,
    "SMART": 78,
    "ASIDE": 38,
    "COYLY": 60,
    "RETCH": 232,
    "START": 104,
    "TIBIA": 45,
    "VOUCH": 21,
    "FOUND": 73,
    "CHEEK": 51,
    "MARSH": 31,
    "POKER": 38,
    "WEDGE": 32,
    "ONSET": 55,
    "THORN": 36,
    "STALK": 70,
    "TIARA": 69,
    "LOWLY": 31,
    "SKILL": 71,
    "FIXER": 306,
    "BOBBY": 82,
    "USING": 33,
    "DRAIN": 55,
    "MONTH": 46,
    "SMELT": 50,
    "GIRTH": 34,
    "SOGGY": 50,
    "NASTY": 65,
    "VOICE": 39,
    "KNOLL": 19,
    "OUTDO": 21,
    "ALBUM": 42,
    "GONER": 24,
    "PHASE": 75,
    "TRICE": 22,
    "DONOR": 69,
    "TANGY": 26,
    "JAUNT": 64,
    "SONIC": 39,
    "BRINK": 41,
    "BELLY": 77,
    "MAJOR": 103,
    "RHYME": 28,
    "ULCER": 71,
    "PUPAL": 40,
    "PAUSE": 30,
    "HEIST": 33,
    "FRESH": 138,
    "OXIDE": 56,
    "BUGGY": 35,
    "PARRY": 127,
    "KARMA": 74,
    "HARRY": 214,
    "TRASH": 40,
    "SHARD": 49,
    "CATER": 46,
    "IRONY": 32,
    "STAFF": 41,
    "SERVE": 38,
    "SPIKE": 96,
    "SCOUR": 30,
    "PAPER": 59,
    "BLUFF": 64,
    "DWARF": 69,
    "FLOAT": 45,
    "DUCHY": 328,
    "LUSTY": 34,
    "INPUT": 52,
    "BLAND": 19,
    "CRAZE": 388,
    "EGRET": 18,
    "EPOCH": 14,
    "CLASS": 31,
    "ALIEN": 28,
    "LINEN": 48,
    "WIDOW": 30,
    "BLOKE": 29,
    "WOVEN": 48,
    "TROLL": 70,
    "BLUSH": 42,
    "SHALL": 38,
    "BRING": 63,
    "GLOAT": 89,
    "AGAPE": 57,
    "REACT": 23,
    "SUGAR": 53,
    "CONIC": 96,
    "ERROR": 22,
    "FLAIR": 26,
    "ADOBE": 100,
    "AUGUR": 28,
    "DOUBT": 41,
    "WEARY": 34,
    "SLOSH": 40,
    "SHIRE": 74,
    "TROPE": 51,
    "GROIN": 52,
    "GLEAN": 32,
    "MOTOR": 50,
    "FOCAL": 37,
    "DEATH": 129,
    "WASTE": 37,
    "HOARD": 52,
    "SLOTH": 76,
    "UNFED": 45,
    "ALLOW": 40,
    "PLANT": 37,
    "THOSE": 26,
    "FOYER": 81,
    "PULPY": 56,
    "ALOFT": 31,
    "MASSE": 41,
    "ASSET": 46,
    "SURER": 55,
    "CHIEF": 35,
    "SHAME": 87,
    "DELTA": 56,
    "FORAY": 38,
    "ACUTE": 41,
    "UPSET": 95,
    "MOTTO": 34,
    "HOWDY": 49,
    "VIGOR": 36,
    "ECLAT": 66,
    "WRUNG": 29,
    "BRIBE": 376,
    "SLUNG": 45,
    "SAUTE": 39,
    "BANAL": 133,
    "CRASS": 54,
    "STINK": 91,
    "CRIMP": 42,
    "FIELD": 72,
    "TRUSS": 54,
    "ARGUE": 11,
    "TAUNT": 50,
    "SCORN": 34,
    "BREAK": 99,
    "BUTCH": 275,
    "SPICY": 30,
    "FEIGN": 38,
    "HUNKY": 53,
    "PRIDE": 54,
    "LOSER": 46,
    "SPRAY": 41,
    "PERKY": 52,
    "CLICK": 77,
    "ESSAY": 41,
    "PROVE": 28,
    "COMMA": 25,
    "DELVE": 49,
    "FLACK": 90,
    "OTHER": 34,
    "SHAWL": 61,
    "BLOWN": 390,
    "ROYAL": 29,
    "LEAVE": 36,
    "PATTY": 35,
    "GAWKY": 33,
    "SNOUT": 49,
    "CYNIC": 46,
    "BOUGH": 48,
    "MIDGE": 61,
    "LIEGE": 43,
    "YEARN": 38,
    "CROAK": 59,
    "PRIMO": 24,
    "STOMP": 48,
    "BIOME": 37,
    "FETUS": 169,
    "DOWRY": 79,
    "GRIME": 418,
    "APRON": 38,
    "QUIET": 13,
    "RUSTY": 37,
    "CRAMP": 70,
    "TIGER": 357,
    "THEME": 43,
    "DEPOT": 88,
    "INTER": 74,
    "LOFTY": 35,
    "MARRY": 305,
    "CHEAT": 38,
    "SIEGE": 41,
    "CHARM": 62,
    "RHINO": 31,
    "LIGHT": 58,
    "LOOPY": 35,
    "FAVOR": 63,
    "AGATE": 151,
    "ISLET": 44,
    "ABACK": 38,
    "THUMB": 39,
    "HAIRY": 220,
    "POUND": 65,
    "PICKY": 27,
    "CAULK": 26,
    "CLOTH": 59,
    "GREAT": 17,
    "SCARE": 17,
    "CRAZY": 39,
    "COMET": 69,
    "DEPTH": 85,
    "GOOSE": 66,
    "SPEND": 52,
    "GRADE": 16,
    "SCRAP": 63,
    "WINCE": 52,
    "PITHY": 17,
    "TRYST": 30,
    "SHRUG": 70,
    "ROBIN": 45,
    "GUILD": 45,
    "GRUEL": 24,
    "LAPEL": 39,
    "TWANG": 24,
    "SMITE": 92,
    "TODAY": 34,
    "TRITE": 30,
    "GOUGE": 81,
    "CINCH": 74,
    "BEING": 43,
    "FRONT": 61,
    "TWICE": 49,
    "AMPLE": 48,
    "GAMER": 46,
    "STOUT": 45,
    "MOUNT": 60,
    "PRICK": 45,
    "REBUS": 33,
    "ROGUE": 55,
    "PANEL": 49,
    "EPOXY": 18,
    "BERTH": 74,
    "BASIC": 32,
    "UNMET": 55,
    "RENEW": 24,
    "PANIC": 43,
    "UNIFY": 55,
    "NIGHT": 78,
    "FINER": 106,
    "WHACK": 44,
    "CRANK": 58,
    "ATONE": 34,
    "SLUMP": 31,
    "STEAD": 29,
    "COULD": 128,
    "LAPSE": 40,
    "RETRO": 60,
    "AROMA": 17,
    "FROTH": 56,
    "AGORA": 31,
    "SEVER": 33,
    "SOLAR": 48,
    "KEBAB": 75,
    "HINGE": 40,
    "DANDY": 34,
    "MIDST": 31,
    "OUGHT": 32,
    "ERODE": 25,
    "REPAY": 22,
    "HASTY": 21,
    "FLICK": 55,
    "APHID": 38,
    "SOOTH": 53,
    "BOOBY": 389,
    "ULTRA": 24,
    "BOOST": 23,
    "MERIT": 30,
    "SCALD": 47,
    "CORNY": 43,
    "LABOR": 99,
    "DRINK": 41,
    "NATAL": 87,
    "FERRY": 43,
    "GAUDY": 40,
    "ALIKE": 31,
    "BOOZY": 394,
    "ABASE": 57,
    "TRAIN": 83,
    "SALAD": 20,
    "WENCH": 58,
    "CREAK": 375,
    "STOOL": 31,
    "VIVID": 36,
    "FARCE": 9,
    "ALTAR": 15,
    "FUNGI": 50,
    "BAYOU": 48,
    "CHAMP": 54,
    "UNLIT": 49,
    "RECAP": 31,
    "TRIAD": 26,
    "THEIR": 20,
    "DROLL": 68,
    "LARVA": 29,
    "DIGIT": 45,
    "USURP": 44,
    "SEEDY": 52,
    "FRAME": 33,
    "HERON": 40,
    "BRAKE": 30,
    "HYDRO": 32,
    "METAL": 57,
    "ROUGE": 310,
    "BRIAR": 17,
    "ELDER": 44,
    "ANGRY": 25,
    "KHAKI": 23,
    "PINTO": 34,
    "HUMOR": 28,
    "CHEST": 34,
    "GROWL": 22,
    "GORGE": 70,
    "CIVIC": 47,
    "CIGAR": 26,
    "FEWER": 20,
    "GLOOM": 44,
    "FOCUS": 34,
    "PLEAT": 88,
    "ZESTY": 68,
    "OLIVE": 45,
    "CHILL": 38,
    "GRIPE": 40,
    "REBUT": 61,
    "TAPIR": 16,
    "BLEED": 16,
    "ABYSS": 27,
    "SQUAD": 19,
    "PILOT": 39
}